LICENSE
README
setup.py
cynpy/KBHit.py
cynpy/__init__.py
cynpy/aardv.py
cynpy/ams.py
cynpy/atm.py
cynpy/basic.py
cynpy/can11xx.py
cynpy/canm0.py
cynpy/cansfr.py
cynpy/csp.py
cynpy/i2c.py
cynpy/init_mac.csh
cynpy/init_win.bat
cynpy/isp.py
cynpy/py_writer.bat
cynpy/py_writer.csh
cynpy/sfrmst.py
cynpy/updprl.py
cynpy.egg-info/PKG-INFO
cynpy.egg-info/SOURCES.txt
cynpy.egg-info/dependency_links.txt
cynpy.egg-info/not-zip-safe
cynpy.egg-info/top_level.txt